metomi/isodatetime/__init__.py
metomi/isodatetime/data.py
metomi/isodatetime/datetimeoper.py
metomi/isodatetime/dumpers.py
metomi/isodatetime/exceptions.py
metomi/isodatetime/main.py
metomi/isodatetime/parser_spec.py
metomi/isodatetime/parsers.py
metomi/isodatetime/timezone.py
metomi/isodatetime/tests/__init__.py
metomi/isodatetime/tests/conftest.py
metomi/isodatetime/tests/test_00.py
metomi/isodatetime/tests/test_01.py
metomi/isodatetime/tests/test_datetimeoper.py
metomi/isodatetime/tests/test_exceptions.py
metomi/isodatetime/tests/test_main.py
metomi/isodatetime/tests/test_time_point.py
metomi/isodatetime/tests/test_timezone.py
metomi_isodatetime-1!3.1.0.dist-info/LICENSE
metomi_isodatetime-1!3.1.0.dist-info/METADATA
metomi_isodatetime-1!3.1.0.dist-info/WHEEL
metomi_isodatetime-1!3.1.0.dist-info/entry_points.txt
metomi_isodatetime-1!3.1.0.dist-info/top_level.txt
metomi_isodatetime-1!3.1.0.dist-info/RECORD
