Metadata-Version: 2.1
Name: metomi-isodatetime
Version: 1!3.1.0
Summary: Python ISO 8601 date time parser and data model/manipulation utilities
Home-page: https://github.com/metomi/isodatetime
Author: Met Office
Author-email: metomi@metoffice.gov.uk
License: LGPLv3
Keywords: isodatetime datetime iso8601 date time parser
Platform: any
Classifier: Development Status :: 5 - Production/Stable
Classifier: Environment :: Other Environment
Classifier: Intended Audience :: Developers
Classifier: License :: OSI Approved :: GNU Lesser General Public License v3 (LGPLv3)
Classifier: Operating System :: OS Independent
Classifier: Programming Language :: Python :: 3.7
Classifier: Programming Language :: Python :: 3.8
Classifier: Programming Language :: Python :: 3.9
Classifier: Programming Language :: Python :: 3.10
Classifier: Programming Language :: Python :: 3.11
Classifier: Programming Language :: Python :: 3 :: Only
Classifier: Topic :: Software Development :: Libraries :: Python Modules
Classifier: Topic :: Utilities
Requires-Python: >=3.7
License-File: LICENSE
Provides-Extra: all
Requires-Dist: coverage ; extra == 'all'
Requires-Dist: pytest >=5 ; extra == 'all'
Requires-Dist: pytest-env ; extra == 'all'
Requires-Dist: pytest-cov ; extra == 'all'
Requires-Dist: flake8 ; extra == 'all'
